main.py
msk_custom_domain/__init__.py
msk_custom_domain/server.py
msk_mcp_server-0.1.5.dist-info/licenses/LICENSE
msk_mm2_mcp_server/__init__.py
msk_mm2_mcp_server/server.py
msk_mcp_server-0.1.5.dist-info/METADATA
msk_mcp_server-0.1.5.dist-info/WHEEL
msk_mcp_server-0.1.5.dist-info/entry_points.txt
msk_mcp_server-0.1.5.dist-info/top_level.txt
msk_mcp_server-0.1.5.dist-info/RECORD
