Metadata-Version: 2.4
Name: msk-mcp-server
Version: 0.1.5
Summary: A Model Context Protocol server for Amazon MSK
Author-email: yhyyz <m18311283082@google.com>
License: MIT
Requires-Python: >=3.9
License-File: LICENSE
Requires-Dist: boto3>=1.38.31
Requires-Dist: botocore>=1.38.31
Requires-Dist: mcp>=1.9.3
Requires-Dist: fastmcp>=2.7.0
Dynamic: license-file
